sembansurga/__init__.py
sembansurga/sembansurga.py
sembansurga-1.1.7.dist-info/METADATA
sembansurga-1.1.7.dist-info/WHEEL
sembansurga-1.1.7.dist-info/top_level.txt
sembansurga-1.1.7.dist-info/RECORD
